FunctionEncoder/__init__.py
FunctionEncoder/Callbacks/BaseCallback.py
FunctionEncoder/Callbacks/DistanceCallback.py
FunctionEncoder/Callbacks/ListCallback.py
FunctionEncoder/Callbacks/MSECallback.py
FunctionEncoder/Callbacks/NLLCallback.py
FunctionEncoder/Callbacks/TensorboardCallback.py
FunctionEncoder/Callbacks/__init__.py
FunctionEncoder/Dataset/BaseDataset.py
FunctionEncoder/Dataset/CIFARDataset.py
FunctionEncoder/Dataset/CategoricalDataset.py
FunctionEncoder/Dataset/EuclideanDataset.py
FunctionEncoder/Dataset/FixedDataset.py
FunctionEncoder/Dataset/GaussianDataset.py
FunctionEncoder/Dataset/GaussianDonutDataset.py
FunctionEncoder/Dataset/QuadraticDataset.py
FunctionEncoder/Dataset/VanDerPolDataset.py
FunctionEncoder/Dataset/__init__.py
FunctionEncoder/Model/FunctionEncoder.py
FunctionEncoder/Model/InnerProduct.py
FunctionEncoder/Model/__init__.py
FunctionEncoder/Model/Architecture/BaseArchitecture.py
FunctionEncoder/Model/Architecture/CNN.py
FunctionEncoder/Model/Architecture/Euclidean.py
FunctionEncoder/Model/Architecture/MLP.py
FunctionEncoder/Model/Architecture/NeuralODE.py
FunctionEncoder/Model/Architecture/ParallelMLP.py
FunctionEncoder/Model/Architecture/build.py
functionencoder-0.2.0.dist-info/METADATA
functionencoder-0.2.0.dist-info/WHEEL
functionencoder-0.2.0.dist-info/top_level.txt
functionencoder-0.2.0.dist-info/RECORD
