Metadata-Version: 2.4
Name: FunctionEncoder
Version: 0.2.0
Summary: A package for learning basis functions over arbitrary function sets. This allows even high-dimensional problems to be solved via a minimal number of basis functions. This allows for zero-shot transfer within these spaces, and also a mechanism for fully informative function representation via the coefficients of the basis functions. Hilbert spaces are nifty.
Author-email: Tyler Ingebrand <tyleringebrand@utexas.edu>
Project-URL: homepage, https://github.com/tyler-ingebrand/FunctionEncoder
Requires-Python: >=3.9
Requires-Dist: torch>=2.0
Requires-Dist: tqdm
Requires-Dist: tensorboard
Requires-Dist: numpy<=1.26.4
